tptp_lark_parser/__init__.py
tptp_lark_parser/cnf_parser.py
tptp_lark_parser/grammar.py
tptp_lark_parser/parse_tptp.py
tptp_lark_parser/py.typed
tptp_lark_parser/resources/TPTP-mock/Axioms/TST001-0.ax
tptp_lark_parser/resources/TPTP-mock/Problems/TST/TST001-1.p
tptp_lark_parser/resources/TPTP.bnf
tptp_lark_parser/resources/TPTP.lark
tptp_lark_parser/resources/tptp_tokens.json
tptp_lark_parser/tptp_parser.py
tptp_lark_parser-0.2.0.dist-info/METADATA
tptp_lark_parser-0.2.0.dist-info/LICENSE
tptp_lark_parser-0.2.0.dist-info/WHEEL
tptp_lark_parser-0.2.0.dist-info/RECORD
