Metadata-Version: 2.1
Name: tptp-lark-parser
Version: 0.2.0
Summary: A TPTP parser using Lark
Home-page: https://github.com/inpefess/tptp-lark-parser
License: Apache-2.0
Author: Boris Shminke
Author-email: boris@shminke.ml
Requires-Python: >=3.7.1,<3.12
Classifier: Development Status :: 7 - Inactive
Classifier: Environment :: Console
Classifier: Intended Audience :: Science/Research
Classifier: License :: OSI Approved :: Apache Software License
Classifier: Natural Language :: English
Classifier: Operating System :: OS Independent
Classifier: Programming Language :: Python :: 3
Classifier: Programming Language :: Python :: 3.8
Classifier: Programming Language :: Python :: 3.9
Classifier: Programming Language :: Python :: 3.10
Classifier: Programming Language :: Python :: 3.11
Classifier: Programming Language :: Python :: 3.10
Classifier: Programming Language :: Python :: 3.11
Classifier: Programming Language :: Python :: 3.7
Classifier: Programming Language :: Python :: 3.8
Classifier: Programming Language :: Python :: 3.9
Classifier: Topic :: Scientific/Engineering :: Mathematics
Classifier: Typing :: Typed
Requires-Dist: importlib_resources ; python_version < "3.9"
Requires-Dist: lark-parser
Project-URL: Repository, https://github.com/inpefess/tptp-lark-parser
